binaryrain_helper_cloud_azure/__init__.py
binaryrain_helper_cloud_azure/azure.py
binaryrain_helper_cloud_azure-0.0.9.dist-info/licenses/LICENSE
binaryrain_helper_cloud_azure-0.0.9.dist-info/METADATA
binaryrain_helper_cloud_azure-0.0.9.dist-info/WHEEL
binaryrain_helper_cloud_azure-0.0.9.dist-info/top_level.txt
binaryrain_helper_cloud_azure-0.0.9.dist-info/RECORD
