Metadata-Version: 2.4
Name: binaryrain-helper-cloud-azure
Version: 0.0.9
Summary: Aims to simplify and help with commonly used functions in the azure cloud data areas.
Author: Binary Rain, Marcel T.O
Project-URL: Homepage, https://binaryrain-net.github.io/Binary-Rain-Helper-Toolkit/
Keywords: binary rain,common,help,functions,azure
Classifier: Programming Language :: Python
Classifier: Programming Language :: Python :: 3
Requires-Python: >=3.10
License-File: LICENSE
Requires-Dist: azure-functions>=1.24.0
Requires-Dist: azure-identity>=1.25.1
Requires-Dist: azure-storage-blob>=12.27.1
Requires-Dist: azure-keyvault-secrets>=4.10.0
Requires-Dist: azure-mgmt-datafactory>=9.2.0
Dynamic: license-file
